parsftp/__init__.py
parsftp/batch.py
parsftp/logger.py
parsftp/maincli.py
parsftp/parsftp.py
parsftp/py.typed
parsftp-0.2.2.dist-info/METADATA
parsftp-0.2.2.dist-info/WHEEL
parsftp-0.2.2.dist-info/entry_points.txt
parsftp-0.2.2.dist-info/top_level.txt
parsftp-0.2.2.dist-info/RECORD
