Metadata-Version: 2.1
Name: parsftp
Version: 0.2.2
Summary: Transfer files through SFTP, launching multiple transfers in parallel.
Author: CNRGH
Author-email: Pierrick ROGER <pierrick.roger@cnrgh.fr>
License: CeCILL
Project-URL: Homepage, https://gitlab.com/cnrgh/parsftp
Project-URL: Repository, https://gitlab.com/cnrgh/parsftp
Project-URL: Bug Tracker, https://gitlab.com/cnrgh/parsftp/issues
Keywords: CNRGH,SFTP,parallel
Classifier: Development Status :: 3 - Alpha
Classifier: Intended Audience :: Science/Research
Classifier: License :: OSI Approved :: CEA CNRS Inria Logiciel Libre License, version 2.1 (CeCILL-2.1)
Classifier: Programming Language :: Python :: 3.11
Requires-Python: >=3.11
Requires-Dist: PyYAML
Requires-Dist: schema
Requires-Dist: colorlog
Provides-Extra: deploy
Requires-Dist: build ; extra == 'deploy'
Requires-Dist: twine ; extra == 'deploy'
Provides-Extra: doc
Requires-Dist: sphinx ; extra == 'doc'
Requires-Dist: sphinx-rtd-theme ; extra == 'doc'
Provides-Extra: tests
Requires-Dist: pytest ; extra == 'tests'
Requires-Dist: mypy ; extra == 'tests'
Requires-Dist: pylint ; extra == 'tests'
Requires-Dist: coverage ; extra == 'tests'
Requires-Dist: yamllint ; extra == 'tests'
Requires-Dist: types-PyYAML ; extra == 'tests'
